{
  "$schema": "https://json-schema.org/draft/2020-12/schema",
  "title": "stream_partition_affinity_integrity schema",
  "type": "object",
  "required": [
    "status",
    "stream_partition_affinity_integrity",
    "failures"
  ],
  "properties": {
    "status": {
      "type": "string",
      "enum": [
        "PASS",
        "FAIL"
      ]
    },
    "stream_partition_affinity_integrity": {
      "type": "object"
    },
    "failures": {
      "type": "array",
      "items": {
        "type": "object"
      }
    }
  }
}